sqlalchemy_tables_copier/__init__.py
sqlalchemy_tables_copier/tables_copier.py
sqlalchemy_tables_copier-0.1.1.dist-info/DESCRIPTION.rst
sqlalchemy_tables_copier-0.1.1.dist-info/METADATA
sqlalchemy_tables_copier-0.1.1.dist-info/RECORD
sqlalchemy_tables_copier-0.1.1.dist-info/WHEEL
sqlalchemy_tables_copier-0.1.1.dist-info/entry_points.txt
sqlalchemy_tables_copier-0.1.1.dist-info/metadata.json
sqlalchemy_tables_copier-0.1.1.dist-info/top_level.txt
