Metadata-Version: 2.0
Name: sqlalchemy-tables-copier
Version: 0.1.1
Summary: Copy tables and their data from one db to another db.
Home-page: https://github.com/fanqingsong/sqlalchemy_tables_copier
Author: Lightsong
Author-email: qsfan@qq.com
License: MIT license
Keywords: sqlalchemy_tables_copier
Platform: UNKNOWN
Classifier: Development Status :: 2 - Pre-Alpha
Classifier: Intended Audience :: Developers
Classifier: License :: OSI Approved :: MIT License
Classifier: Natural Language :: English
Classifier: Programming Language :: Python :: 3
Classifier: Programming Language :: Python :: 3.6
Classifier: Programming Language :: Python :: 3.7
Classifier: Programming Language :: Python :: 3.8
Requires-Python: >=3.6
Requires-Dist: Click (>=7.0)
